scmodels/__init__.py
scmodels/parser.py
scmodels/scm.py
scmodels-0.3.1.dist-info/LICENSE.md
scmodels-0.3.1.dist-info/METADATA
scmodels-0.3.1.dist-info/WHEEL
scmodels-0.3.1.dist-info/top_level.txt
scmodels-0.3.1.dist-info/RECORD
