Metadata-Version: 2.1
Name: scmodels
Version: 0.3.1
Summary: Structural Causal Models
Author-email: Michael Aichmueller <m.aichmueller@gmail.com>
License: 
Project-URL: Source, https://github.com/maichmueller/scmodels
Keywords: bayesian-graphs,graphical-models,scm,sem,fcm
Classifier: Development Status :: 3 - Alpha
Classifier: Intended Audience :: Science/Research
Classifier: License :: OSI Approved :: MIT License
Classifier: Natural Language :: English
Classifier: Programming Language :: Python :: 3.7
Classifier: Operating System :: MacOS :: MacOS X
Classifier: Operating System :: Microsoft :: Windows
Classifier: Operating System :: POSIX :: Linux
Classifier: Topic :: Scientific/Engineering :: Mathematics
License-File: LICENSE.md
Requires-Dist: numpy >=1.19
Requires-Dist: scipy >=1.3
Requires-Dist: pandas >=1.0
Requires-Dist: matplotlib >=3.0
Requires-Dist: sympy >=1.9.0
Requires-Dist: networkx >=2.0
Provides-Extra: dev
Requires-Dist: pytest ; extra == 'dev'
Requires-Dist: pytest-cov ; extra == 'dev'
